MANIFEST.in
README.rst
setup.py
collective/.DS_Store
collective/__init__.py
collective/__init__.pyc
collective.ptg.contactsheet.egg-info/PKG-INFO
collective.ptg.contactsheet.egg-info/SOURCES.txt
collective.ptg.contactsheet.egg-info/dependency_links.txt
collective.ptg.contactsheet.egg-info/entry_points.txt
collective.ptg.contactsheet.egg-info/namespace_packages.txt
collective.ptg.contactsheet.egg-info/not-zip-safe
collective.ptg.contactsheet.egg-info/requires.txt
collective.ptg.contactsheet.egg-info/top_level.txt
collective/ptg/.DS_Store
collective/ptg/__init__.py
collective/ptg/__init__.pyc
collective/ptg/contactsheet/.DS_Store
collective/ptg/contactsheet/__init__.py
collective/ptg/contactsheet/__init__.pyc
collective/ptg/contactsheet/configure.zcml
collective/ptg/contactsheet/contactsheet.pt
collective/ptg/contactsheet/i18n.sh
collective/ptg/contactsheet/locales/collective.ptg.contactsheet.pot
collective/ptg/contactsheet/locales/manual.pot
collective/ptg/contactsheet/locales/de/LC_MESSAGES/collective.ptg.contactsheet.mo
collective/ptg/contactsheet/locales/de/LC_MESSAGES/collective.ptg.contactsheet.po
collective/ptg/contactsheet/locales/es/LC_MESSAGES/collective.ptg.contactsheet.mo
collective/ptg/contactsheet/locales/es/LC_MESSAGES/collective.ptg.contactsheet.po
collective/ptg/contactsheet/locales/eu/LC_MESSAGES/collective.ptg.contactsheet.po
collective/ptg/contactsheet/locales/fi/LC_MESSAGES/collective.ptg.contactsheet.po
collective/ptg/contactsheet/locales/fr/LC_MESSAGES/collective.ptg.contactsheet.mo
collective/ptg/contactsheet/locales/fr/LC_MESSAGES/collective.ptg.contactsheet.po
collective/ptg/contactsheet/locales/it/LC_MESSAGES/collective.ptg.contactsheet.po
collective/ptg/contactsheet/locales/nl/LC_MESSAGES/collective.ptg.contactsheet.po
collective/ptg/contactsheet/locales/no/LC_MESSAGES/collective.ptg.contactsheet.mo
collective/ptg/contactsheet/locales/no/LC_MESSAGES/collective.ptg.contactsheet.po
collective/ptg/contactsheet/locales/pt_BR/LC_MESSAGES/collective.ptg.contactsheet.po
collective/ptg/contactsheet/resources/icon_style.css
collective/ptg/contactsheet/resources/icon_style_ii.css
collective/ptg/contactsheet/resources/icon_style_iii.css
collective/ptg/contactsheet/resources/no_style.css
collective/ptg/contactsheet/resources/style.css
docs/HISTORY.txt
docs/INSTALL.txt
docs/LICENSE.GPL
docs/LICENSE.txt