Metadata-Version: 1.0
Name: collective.ptg.contactsheet
Version: 1.1.2
Summary: Contact sheet gallery type for plonetruegallery
Home-page: https://github.com/collective/collective.ptg.contactsheet
Author: Nathan Van Gheem
Author-email: vangheem@gmail.com
License: GPL
Keywords: plonetruegaller gallery plone addon
Platform: UNKNOWN
Classifier: Framework :: Plone
Classifier: Programming Language :: Python
